README
setup.py
mynt_cust_model/__init__.py
mynt_cust_model.egg-info/PKG-INFO
mynt_cust_model.egg-info/SOURCES.txt
mynt_cust_model.egg-info/dependency_links.txt
mynt_cust_model.egg-info/not-zip-safe
mynt_cust_model.egg-info/top_level.txt