Metadata-Version: 1.0
Name: mynt-cust-model
Version: 1.5
Summary: Custom model for size recommendation
Home-page: http://github.com/storborg/funniest
Author: Abdulla
Author-email: ghani.abdulla@myntra.com
License: MIT
Platform: UNKNOWN
